fipie/__init__.py
fipie/cluster.py
fipie/common.py
fipie/data.py
fipie/date.py
fipie/portfolio.py
fipie/tree.py
fipie/version.py
fipie/weighting.py
fipie/data/price.csv
tests/__init__.py
tests/test_cluster.py
tests/test_common.py
tests/test_data.py
tests/test_date.py
tests/test_portfolio.py
tests/test_tree.py
tests/test_weighting.py
fipie-0.0.6.dist-info/LICENSE
fipie-0.0.6.dist-info/METADATA
fipie-0.0.6.dist-info/WHEEL
fipie-0.0.6.dist-info/top_level.txt
fipie-0.0.6.dist-info/RECORD
