Metadata-Version: 2.1
Name: fipie
Version: 0.0.6
Summary: A simple portfolio optimiser beyond the mean-variance optimisation
Home-page: https://github.com/thoriuchi0531/fipie
Author: Tomoya Horiuchi
Author-email: thoriuchi0531@gmail.com
License: MIT
Project-URL: Documentation, https://fipie.readthedocs.io/en/latest/
Project-URL: Source, https://github.com/thoriuchi0531/fipie
Keywords: finance,investing,portfolio-optimization,quantitative-finance,portfolio-management
Platform: UNKNOWN
Classifier: Development Status :: 3 - Alpha
Classifier: License :: OSI Approved :: MIT License
Classifier: Programming Language :: Python :: 3.6
Classifier: Programming Language :: Python :: 3.7
Classifier: Programming Language :: Python :: 3.8
Classifier: Programming Language :: Python :: 3.9
Classifier: Topic :: Office/Business :: Financial :: Investment
Requires-Python: >=3.6
License-File: LICENSE
Requires-Dist: pandas (>=0.25)
Requires-Dist: scipy (>=1.0)
Provides-Extra: dev
Requires-Dist: pytest (>=6.2.5) ; extra == 'dev'
Requires-Dist: coverage (>=6.0.2) ; extra == 'dev'
Requires-Dist: sphinx (==4.2.0) ; extra == 'dev'
Requires-Dist: sphinx-book-theme (==0.1.6) ; extra == 'dev'
Requires-Dist: myst-parser (==0.15.2) ; extra == 'dev'
